newrelic/__init__.py
newrelic/_version.py
newrelic/agent.py
newrelic/config.py
newrelic/console.py
newrelic/newrelic.ini
newrelic/admin/__init__.py
newrelic/admin/__main__.py
newrelic/admin/debug_console.py
newrelic/admin/generate_config.py
newrelic/admin/license_key.py
newrelic/admin/local_config.py
newrelic/admin/network_config.py
newrelic/admin/record_deploy.py
newrelic/admin/run_program.py
newrelic/admin/run_python.py
newrelic/admin/server_config.py
newrelic/admin/validate_config.py
newrelic/api/__init__.py
newrelic/api/application.py
newrelic/api/asgi_application.py
newrelic/api/background_task.py
newrelic/api/cat_header_mixin.py
newrelic/api/database_trace.py
newrelic/api/datastore_trace.py
newrelic/api/error_trace.py
newrelic/api/exceptions.py
newrelic/api/external_trace.py
newrelic/api/function_profile.py
newrelic/api/function_trace.py
newrelic/api/generator_trace.py
newrelic/api/graphql_trace.py
newrelic/api/html_insertion.py
newrelic/api/import_hook.py
newrelic/api/llm_custom_attributes.py
newrelic/api/log.py
newrelic/api/memcache_trace.py
newrelic/api/message_trace.py
newrelic/api/message_transaction.py
newrelic/api/ml_model.py
newrelic/api/object_wrapper.py
newrelic/api/profile_trace.py
newrelic/api/settings.py
newrelic/api/solr_trace.py
newrelic/api/supportability.py
newrelic/api/time_trace.py
newrelic/api/transaction.py
newrelic/api/transaction_name.py
newrelic/api/web_transaction.py
newrelic/api/wsgi_application.py
newrelic/bootstrap/__init__.py
newrelic/bootstrap/sitecustomize.py
newrelic/common/__init__.py
newrelic/common/agent_http.py
newrelic/common/async_proxy.py
newrelic/common/async_wrapper.py
newrelic/common/cacert.pem
newrelic/common/certs.py
newrelic/common/coroutine.py
newrelic/common/encoding_utils.py
newrelic/common/llm_utils.py
newrelic/common/log_file.py
newrelic/common/metric_utils.py
newrelic/common/object_names.py
newrelic/common/object_wrapper.py
newrelic-11.4.0.dist-info/METADATA
newrelic-11.4.0.dist-info/WHEEL
newrelic-11.4.0.dist-info/entry_points.txt
newrelic-11.4.0.dist-info/top_level.txt
newrelic-11.4.0.dist-info/RECORD
newrelic-11.4.0.dist-info/licenses/LICENSE
