Metadata-Version: 2.4
Name: newrelic
Version: 11.4.0
Summary: New Relic Python Agent
Author-email: New Relic <support@newrelic.com>
Maintainer-email: New Relic <support@newrelic.com>
License: Apache-2.0
Project-URL: Homepage, https://docs.newrelic.com/docs/apm/agents/python-agent/
Project-URL: GitHub, https://github.com/newrelic/newrelic-python-agent
Project-URL: Release Notes, https://docs.newrelic.com/docs/release-notes/agent-release-notes/python-release-notes/
Classifier: Development Status :: 5 - Production/Stable
Classifier: Programming Language :: Python :: 3.8
Classifier: Programming Language :: Python :: 3.9
Classifier: Programming Language :: Python :: 3.10
Classifier: Programming Language :: Python :: 3.11
Classifier: Programming Language :: Python :: 3.12
Classifier: Programming Language :: Python :: 3.13
Classifier: Programming Language :: Python :: 3.14
Classifier: Programming Language :: Python :: Implementation :: CPython
Classifier: Programming Language :: Python :: Implementation :: PyPy
Classifier: Topic :: System :: Monitoring
Requires-Python: >=3.8
License-File: LICENSE
Provides-Extra: infinite-tracing
Requires-Dist: grpcio; extra == "infinite-tracing"
Requires-Dist: protobuf; extra == "infinite-tracing"
Dynamic: license
Dynamic: license-file
